py_setr-0.1.1.dist-info/licenses/LICENSE
setr/__init__.py
setr/cil_extensions/__init__.py
setr/cil_extensions/callbacks/__init__.py
setr/cil_extensions/callbacks/callbacks.py
setr/cil_extensions/framework/__init__.py
setr/cil_extensions/framework/framework.py
setr/cil_extensions/functions/__init__.py
setr/cil_extensions/functions/functions.py
setr/cil_extensions/operators/__init__.py
setr/cil_extensions/operators/operators.py
setr/cil_extensions/preconditioners/__init__.py
setr/cil_extensions/preconditioners/preconditioners.py
setr/cil_extensions/utilities/__init__.py
setr/cil_extensions/utilities/utilities.py
setr/core/__init__.py
setr/core/gradients/__init__.py
setr/core/gradients/gradients.py
setr/kernel/__init__.py
setr/kernel/python/__init__.py
setr/kernel/python/my_kem.py
setr/kernel/stir/__init__.py
setr/kernel/stir/stir_kem.py
setr/priors/__init__.py
setr/priors/mutual_information.py
setr/priors/vtv/schatten_norm_cpu.py
setr/priors/vtv/schatten_norm_gpu.py
setr/priors/vtv/schatten_norm_gpu_slow.py
setr/priors/vtv/vector_norm.py
setr/priors/vtv/vtv.py
setr/utils/__init__.py
setr/utils/cil.py
setr/utils/io.py
setr/utils/nifty.py
setr/utils/sirf.py
py_setr-0.1.1.dist-info/METADATA
py_setr-0.1.1.dist-info/WHEEL
py_setr-0.1.1.dist-info/entry_points.txt
py_setr-0.1.1.dist-info/top_level.txt
py_setr-0.1.1.dist-info/RECORD
